fast_table_detect/__init__.py
fast_table_detect/detect.py
fast_table_detect/detect_gutter.py
fast_table_detect/detect_lines.py
fast_table_detect/preprocess.py
fast_table_detect/utils.py
fast_table_detect-0.1.0.dist-info/licenses/LICENSE
fast_table_detect-0.1.0.dist-info/METADATA
fast_table_detect-0.1.0.dist-info/WHEEL
fast_table_detect-0.1.0.dist-info/top_level.txt
fast_table_detect-0.1.0.dist-info/RECORD
