Metadata-Version: 2.4
Name: fast-table-detect
Version: 0.1.0
Summary: A Python package for fast table detection
Author-email: Samuel Diop <snfdiop@outlook.com>
License: MIT
Project-URL: Homepage, https://github.com/Slownite/fast-table-detect
Project-URL: Repository, https://github.com/Slownite/fast-table-detect
Classifier: Development Status :: 3 - Alpha
Classifier: Intended Audience :: Developers
Classifier: License :: OSI Approved :: MIT License
Classifier: Programming Language :: Python :: 3
Classifier: Programming Language :: Python :: 3.8
Classifier: Programming Language :: Python :: 3.9
Classifier: Programming Language :: Python :: 3.10
Classifier: Programming Language :: Python :: 3.11
Requires-Python: >=3.8
License-File: LICENSE
Requires-Dist: numpy
Requires-Dist: opencv-python
Requires-Dist: scikit-learn
Requires-Dist: pillow
Requires-Dist: matplotlib
Requires-Dist: tqdm
Provides-Extra: dev
Requires-Dist: pytest; extra == "dev"
Requires-Dist: black; extra == "dev"
Requires-Dist: flake8; extra == "dev"
Requires-Dist: mypy; extra == "dev"
Dynamic: license-file
